mycall/__init__.py
mycall_parth/__init__.py
mycall_parth-0.0.1.dist-info/METADATA
mycall_parth-0.0.1.dist-info/WHEEL
mycall_parth-0.0.1.dist-info/top_level.txt
mycall_parth-0.0.1.dist-info/RECORD
